{
  "pages": [
    {
      "path": "pages/login/index",
      "style": {
        "navigationBarTitleText": "登录",
        "navigationStyle": "custom"
      }
    },
    {
      "path": "pages/workbench/index",
      "style": {
        "navigationBarTitleText": "工作台",
        "navigationStyle": "custom"
      }
    },
    {
      "path": "pages/tasks/index",
      "style": {
        "navigationBarTitleText": "历史",
        "navigationStyle": "custom"
      }
    },
    {
      "path": "pages/resources/index",
      "style": {
        "navigationBarTitleText": "资源库",
        "navigationStyle": "custom"
      }
    },
    {
      "path": "pages/mine/index",
      "style": {
        "navigationBarTitleText": "我的",
        "navigationStyle": "custom"
      }
    },
    {
      "path": "pages/quota/index",
      "style": {
        "navigationBarTitleText": "额度明细",
        "navigationStyle": "custom"
      }
    },
    {
      "path": "pages/feedback/index",
      "style": {
        "navigationBarTitleText": "问题反馈",
        "navigationStyle": "custom"
      }
    },
    {
      "path": "pages/announcements/index",
      "style": {
        "navigationBarTitleText": "公告邮箱",
        "navigationStyle": "custom"
      }
    },
    {
      "path": "pages/promotion/index",
      "style": {
        "navigationBarTitleText": "推荐收益",
        "navigationStyle": "custom"
      }
    },
    {
      "path": "pages/users/index",
      "style": {
        "navigationBarTitleText": "用户管理",
        "navigationStyle": "custom"
      }
    }
  ],
  "globalStyle": {
    "navigationBarTextStyle": "white",
    "navigationBarTitleText": "勋港家具 AI",
    "navigationBarBackgroundColor": "#07080a",
    "backgroundColor": "#07080a",
    "navigationStyle": "custom"
  },
  "uniIdRouter": {}
}
